{
  "name": "99: Supplies",
  "icon": "minecraft:writable_book",
  "category": "questown:entries",
  "advancement": "questown:first_job_block",
  "pages": [
    {
      "type": "patchouli:text",
      "text": "Now that your villager has somewhere to work, they will be looking for supplies. Have you built a store room yet?$(br2)Build a store room, then fill the chest with a few supplies."
    }, {
      "type": "patchouli:multiblock",
      "multiblock": {
        "mapping": {
          "W": "minecraft:oak_planks",
          "D": "minecraft:oak_door[facing=west]",
          "T": "minecraft:oak_door[facing=west,half=upper]",
          "X": "minecraft:chest[facing=east]",
          "R": "minecraft:wall_torch[facing=east]"
        },
        "pattern": [
          ["WWWW", " R  ", "    ", "    "],
          ["WWWW", "W XW", "W 0W", "WWDW"]
        ]
      },
      "text": "Hint: Right-click on your villager to see what supplies they need."
    }
  ]
}
